CoREMOF/__init__.py
CoREMOF/curate.py
CoREMOF/prediction.py
CoREMOF/structure.py
CoREMOF/calculation/Zeopp.py
CoREMOF/calculation/__init__.py
CoREMOF/calculation/atomic_parameters.py
CoREMOF/calculation/mof.py
CoREMOF/calculation/mof_collection.py
CoREMOF/calculation/mof_features.py
CoREMOF/models/__init__.py
CoREMOF/models/cp_app/__init__.py
CoREMOF/models/cp_app/descriptors.py
CoREMOF/models/cp_app/featurizer.py
CoREMOF/models/cp_app/generate_labels.py
CoREMOF/models/cp_app/predictions.py
CoREMOF/models/cp_app/utils.py
CoREMOF/models/cp_app/versions.py
CoREMOF/utils/__init__.py
CoREMOF/utils/atoms_definitions.py
CoREMOF/utils/expensive_rare_metal.py
CoREMOF/utils/ions_list.py
CoREMOF/utils/remove.py
CoREMOF_tools-1.1.0.dist-info/METADATA
CoREMOF_tools-1.1.0.dist-info/WHEEL
CoREMOF_tools-1.1.0.dist-info/top_level.txt
CoREMOF_tools-1.1.0.dist-info/RECORD
