Metadata-Version: 2.1
Name: CoREMOF-tools
Version: 1.1.0
Summary: Python API for CoRE MOF 2024 DB
Home-page: https://github.com/mtap-research/CoRE-MOF-Tools
Author: Guobin Zhao
Author-email: sxmzhaogb@gmail.com
Classifier: Development Status :: 3 - Alpha
Classifier: Intended Audience :: Developers
Classifier: Topic :: Software Development :: Build Tools
Classifier: License :: OSI Approved :: MIT License
Classifier: Programming Language :: Python :: 3
Classifier: Programming Language :: Python :: 3.9
Requires-Python: >=3.9, <4
Requires-Dist: pymatgen
Requires-Dist: ase
Requires-Dist: juliacall
Requires-Dist: molSimplify
Requires-Dist: PACMAN-charge
Requires-Dist: cloudpickle
Requires-Dist: matminer
Requires-Dist: xgboost
Requires-Dist: scikit-learn (==1.3.2)
Requires-Dist: mofchecker
Provides-Extra: zeopp
Requires-Dist: zeopp-lsmo ; extra == 'zeopp'
